InfanTSeg/__init__.py
data/__init__.py
InfanTSeg-0.0.1.dist-info/LICENSE
InfanTSeg-0.0.1.dist-info/METADATA
InfanTSeg-0.0.1.dist-info/WHEEL
InfanTSeg-0.0.1.dist-info/top_level.txt
InfanTSeg-0.0.1.dist-info/RECORD
