Metadata-Version: 2.1
Name: InfanTSeg
Version: 0.0.1
Summary: Infant Brain Tissue Segmentation Tools
Home-page: https://github.com/SaberPRC/Auto-BET
Author: Jiameng Liu
Author-email: JiamengLiu.PRC@gmail.com
Classifier: Programming Language :: Python :: 3
Classifier: License :: OSI Approved :: MIT License
Classifier: Operating System :: OS Independent
License-File: LICENSE
Requires-Dist: antspyx
Requires-Dist: numpy
Requires-Dist: pandas
Requires-Dist: torch
Requires-Dist: SimpleITK
Requires-Dist: MIDP
Requires-Dist: tqdm
